shivmlpro/__init__.py
shivmlpro/mlmodels.py
shivmlpro-0.2.dist-info/METADATA
shivmlpro-0.2.dist-info/WHEEL
shivmlpro-0.2.dist-info/top_level.txt
shivmlpro-0.2.dist-info/RECORD
